odoo/addons/contract_digitized_signature/README.rst
odoo/addons/contract_digitized_signature/__init__.py
odoo/addons/contract_digitized_signature/__manifest__.py
odoo/addons/contract_digitized_signature/i18n/ca.po
odoo/addons/contract_digitized_signature/i18n/contract_digitized_signature.pot
odoo/addons/contract_digitized_signature/i18n/de.po
odoo/addons/contract_digitized_signature/i18n/el_GR.po
odoo/addons/contract_digitized_signature/i18n/es.po
odoo/addons/contract_digitized_signature/i18n/es_MX.po
odoo/addons/contract_digitized_signature/i18n/fi.po
odoo/addons/contract_digitized_signature/i18n/fr.po
odoo/addons/contract_digitized_signature/i18n/gl.po
odoo/addons/contract_digitized_signature/i18n/hi_IN.po
odoo/addons/contract_digitized_signature/i18n/hr.po
odoo/addons/contract_digitized_signature/i18n/hr_HR.po
odoo/addons/contract_digitized_signature/i18n/hu.po
odoo/addons/contract_digitized_signature/i18n/it.po
odoo/addons/contract_digitized_signature/i18n/nl.po
odoo/addons/contract_digitized_signature/i18n/pt.po
odoo/addons/contract_digitized_signature/i18n/pt_BR.po
odoo/addons/contract_digitized_signature/i18n/pt_PT.po
odoo/addons/contract_digitized_signature/i18n/ro.po
odoo/addons/contract_digitized_signature/i18n/ru.po
odoo/addons/contract_digitized_signature/i18n/sk_SK.po
odoo/addons/contract_digitized_signature/i18n/sl.po
odoo/addons/contract_digitized_signature/i18n/tr.po
odoo/addons/contract_digitized_signature/i18n/tr_TR.po
odoo/addons/contract_digitized_signature/i18n/zh_CN.po
odoo/addons/contract_digitized_signature/models/__init__.py
odoo/addons/contract_digitized_signature/models/account_analytic_account.py
odoo/addons/contract_digitized_signature/readme/CONTRIBUTORS.rst
odoo/addons/contract_digitized_signature/readme/DESCRIPTION.rst
odoo/addons/contract_digitized_signature/readme/INSTALL.rst
odoo/addons/contract_digitized_signature/readme/USAGE.rst
odoo/addons/contract_digitized_signature/report/report_contract.xml
odoo11_addon_contract_digitized_signature-11.0.1.0.0.99.dev9.dist-info/METADATA
odoo11_addon_contract_digitized_signature-11.0.1.0.0.99.dev9.dist-info/WHEEL
odoo11_addon_contract_digitized_signature-11.0.1.0.0.99.dev9.dist-info/top_level.txt
odoo11_addon_contract_digitized_signature-11.0.1.0.0.99.dev9.dist-info/RECORD
